Metadata-Version: 2.1
Name: TScript
Version: 1.0.0
Author: SneakyFrameworkCreator
Classifier: Development Status :: 1 - Planning
Classifier: Environment :: Other Environment
Classifier: License :: OSI Approved :: MIT License
Classifier: Operating System :: Microsoft :: Windows :: Windows 11
Classifier: Operating System :: OS Independent
Classifier: Programming Language :: Python
Classifier: Programming Language :: Python :: Implementation
Classifier: Topic :: Scientific/Engineering :: Mathematics
Classifier: Topic :: Software Development :: Libraries :: Application Frameworks
